{

"images": [
    "/games/Illusionist/source/RES/J.png"
],

"framerate": 2,
"frames": [
    [1, 1, 100, 100, 0, 0, 0],
    [103, 1, 100, 100, 0, 0, 0]
],

"animations": {
    "J_A": { "frames": [0] },
    "J_B": { "frames": [1] }
},

"texturepacker": [
        "SmartUpdateHash: $TexturePacker:SmartUpdate:e7d4ffe7caf1c6969c80614ce2e412ea:5fa04e77c72467c070be56eb29e69bc1:5832dd710832637990d7f2e6d83d5914$",
        "Created with TexturePacker (https://www.codeandweb.com/texturepacker) for EaselJS"
]

}
