{

"images": [
    "/games/TreasureCastle/source/RES/J.png"
],

"framerate": 2,
"frames": [
    [1, 1, 100, 100, 0, 0, 0],
    [103, 1, 100, 100, 0, 0, 0]
],

"animations": {
    "J_A": { "frames": [0] },
    "J_B": { "frames": [1] }
},

"texturepacker": [
        "SmartUpdateHash: $TexturePacker:SmartUpdate:70f526d4dc18089e881dddafd961dbfe:06399fdae96cb83c9f0f8d831d97742a:5832dd710832637990d7f2e6d83d5914$",
        "Created with TexturePacker (https://www.codeandweb.com/texturepacker) for EaselJS"
]

}
