{

"images": [
    "/games/BookOfRa/source/RES/10.png"
],

"framerate": 3,
"frames": [
    [1, 1, 100, 100, 0, 0, 0],
    [103, 1, 100, 100, 0, 0, 0]
],

"animations": {
    "10_A": { "frames": [0] },
    "10_B": { "frames": [1] }
},

"texturepacker": [
        "SmartUpdateHash: $TexturePacker:SmartUpdate:ffee0832a1a4195b58eae0da54c13a92:181ca5b034f3612329259cc48c2c1bfa:e2c9be1b49d03cc38aafeff96da146a7$",
        "Created with TexturePacker (https://www.codeandweb.com/texturepacker) for EaselJS"
]

}
