{

"images": [
    "/games/FirstClassTraveller/source/RES/J.png"
],

"framerate": 5,
"frames": [
    [1, 1, 100, 100, 0, 0, 0],
    [103, 1, 100, 100, 0, 0, 0]
],

"animations": {
    "J_A": { "frames": [0] },
    "J_B": { "frames": [1] }
},

"texturepacker": [
        "SmartUpdateHash: $TexturePacker:SmartUpdate:7811159e838c159d12790ab6046d94ae:6865f16d87d59015a351251b21ff6bcc:5832dd710832637990d7f2e6d83d5914$",
        "Created with TexturePacker (https://www.codeandweb.com/texturepacker) for EaselJS"
]

}
