{

"images": [
    "/games/Football/source/RES/J.png"
],

"framerate": 5,
"frames": [
    [1, 1, 100, 100, 0, 0, 0],
    [103, 1, 100, 100, 0, 0, 0]
],

"animations": {
    "J_A": { "frames": [0] },
    "J_B": { "frames": [1] }
},

"texturepacker": [
        "SmartUpdateHash: $TexturePacker:SmartUpdate:3392e5eb32a2a15b7ebb3dab47c9d4bf:af8558db8e94fc4be7f4fdf65af9cc5a:5832dd710832637990d7f2e6d83d5914$",
        "Created with TexturePacker (https://www.codeandweb.com/texturepacker) for EaselJS"
]

}
