{

"images": [
    "/games/Sparta/source/RES/Q.png"
],

"framerate": 2,
"frames": [
    [1, 1, 100, 100, 0, 0, 0],
    [1, 103, 100, 100, 0, 0, 0],
    [1, 205, 100, 100, 0, 0, 0],
    [1, 307, 100, 100, 0, 0, 0],
    [1, 409, 100, 100, 0, 0, 0],
    [103, 1, 100, 100, 0, 0, 0],
    [205, 1, 100, 100, 0, 0, 0],
    [307, 1, 100, 100, 0, 0, 0],
    [409, 1, 100, 100, 0, 0, 0],
    [103, 103, 100, 100, 0, 0, 0],
    [103, 205, 100, 100, 0, 0, 0],
    [103, 307, 100, 100, 0, 0, 0],
    [103, 409, 100, 100, 0, 0, 0],
    [205, 103, 100, 100, 0, 0, 0],
    [307, 103, 100, 100, 0, 0, 0],
    [409, 103, 100, 100, 0, 0, 0],
    [205, 205, 100, 100, 0, 0, 0],
    [205, 307, 100, 100, 0, 0, 0],
    [205, 409, 100, 100, 0, 0, 0],
    [307, 205, 100, 100, 0, 0, 0],
    [409, 205, 100, 100, 0, 0, 0],
    [307, 307, 100, 100, 0, 0, 0],
    [307, 409, 100, 100, 0, 0, 0],
    [409, 307, 100, 100, 0, 0, 0],
    [409, 409, 100, 100, 0, 0, 0]
],

"animations": {
    "Q_A": { "frames": [0] },
    "Q_B": { "frames": [1] },
    "Q_C": { "frames": [2] },
    "Q_D": { "frames": [3] },
    "Q_E": { "frames": [4] },
    "Q_F": { "frames": [5] },
    "Q_G": { "frames": [6] },
    "Q_H": { "frames": [7] },
    "Q_I": { "frames": [8] },
    "Q_J": { "frames": [9] },
    "Q_K": { "frames": [10] },
    "Q_L": { "frames": [11] },
    "Q_M": { "frames": [12] },
    "Q_N": { "frames": [13] },
    "Q_O": { "frames": [14] },
    "Q_P": { "frames": [15] },
    "Q_Q": { "frames": [16] },
    "Q_R": { "frames": [17] },
    "Q_S": { "frames": [18] },
    "Q_T": { "frames": [19] },
    "Q_U": { "frames": [20] },
    "Q_V": { "frames": [21] },
    "Q_W": { "frames": [22] },
    "Q_X": { "frames": [23] },
    "Q_Y": { "frames": [24] }
},

"texturepacker": [
        "SmartUpdateHash: $TexturePacker:SmartUpdate:7a59c4dcdf59e9df499505c02ffaf121:9bcbac4e72257e446c503bae2c0273bc:6d77ca9c310e3e5f270ff183996e3fbf$",
        "Created with TexturePacker (https://www.codeandweb.com/texturepacker) for EaselJS"
]

}
