{

"images": [
    "/games/DiamondTrio/source/RES/J.png"
],

"framerate": 5,
"frames": [
    [1, 1, 100, 100, 0, 0, 0],
    [103, 1, 100, 100, 0, 0, 0],
    [205, 1, 100, 100, 0, 0, 0]
],

"animations": {
    "J_A": { "frames": [0] },
    "J_B": { "frames": [1] },
    "J_C": { "frames": [2] }
},

"texturepacker": [
        "SmartUpdateHash: $TexturePacker:SmartUpdate:cf371a56bb20b3166c4914d673b9205a:065c2c4bdfe3f37dbc104b1ff761b22d:5832dd710832637990d7f2e6d83d5914$",
        "Created with TexturePacker (https://www.codeandweb.com/texturepacker) for EaselJS"
]

}
