{"frames": {

"SCAT_LONG_A":
{
	"frame": {"x":1,"y":1,"w":248,"h":248},
	"rotated": false,
	"trimmed": false,
	"spriteSourceSize": {"x":0,"y":0,"w":248,"h":248},
	"sourceSize": {"w":248,"h":248}
},
"SCAT_LONG_B":
{
	"frame": {"x":1,"y":251,"w":248,"h":248},
	"rotated": false,
	"trimmed": false,
	"spriteSourceSize": {"x":0,"y":0,"w":248,"h":248},
	"sourceSize": {"w":248,"h":248}
}},
"meta": {
	"app": "https://www.codeandweb.com/texturepacker",
	"version": "1.0",
	"image": "SCAT_LONG.png",
	"format": "RGBA8888",
	"size": {"w":512,"h":512},
	"scale": "1",
	"smartupdate": "$TexturePacker:SmartUpdate:bb5b5e11fe293c881aad8dabef7971cb:7c7535ac9641b32025a3406f417c5866:4e9b7563a8495434135995f57fdf4cad$"
}
}
