{

"images": [
    "/games/PolarFox/source/RES/10.png"
],

"framerate": 2,
"frames": [
    [1, 1, 100, 100, 0, 0, 0],
    [103, 1, 100, 100, 0, 0, 0]
],

"animations": {
    "10_A": { "frames": [0] },
    "10_B": { "frames": [1] }
},

"texturepacker": [
        "SmartUpdateHash: $TexturePacker:SmartUpdate:e056759565ed2a45daf7607cc3308cfc:549597a7950817939faa094a1ae1035d:3f11b13715d8c7c6894c81e1d926f2eb$",
        "Created with TexturePacker (https://www.codeandweb.com/texturepacker) for EaselJS"
]

}
