{

"images": [
    "/games/KingOfCash/source/RES/Q.png"
],

"framerate": 2,
"frames": [
    [1, 1, 100, 100, 0, 0, 0],
    [103, 1, 100, 100, 0, 0, 0]
],

"animations": {
    "Q_A": { "frames": [0] },
    "Q_B": { "frames": [1] }
},

"texturepacker": [
        "SmartUpdateHash: $TexturePacker:SmartUpdate:7824ec1e7a0cf547eec95dc212bc42ff:99635bde65f8e6e9c325dd1af38ba67e:fedce6eec9187e32f2ed73c78dbc37b0$",
        "Created with TexturePacker (https://www.codeandweb.com/texturepacker) for EaselJS"
]

}
