{"frames": {

"P_1_WILD_A":
{
	"frame": {"x":1,"y":1,"w":248,"h":248},
	"rotated": false,
	"trimmed": false,
	"spriteSourceSize": {"x":0,"y":0,"w":248,"h":248},
	"sourceSize": {"w":248,"h":248}
},
"P_1_WILD_B":
{
	"frame": {"x":1,"y":251,"w":248,"h":248},
	"rotated": false,
	"trimmed": false,
	"spriteSourceSize": {"x":0,"y":0,"w":248,"h":248},
	"sourceSize": {"w":248,"h":248}
},
"P_1_WILD_C":
{
	"frame": {"x":1,"y":501,"w":248,"h":248},
	"rotated": false,
	"trimmed": false,
	"spriteSourceSize": {"x":0,"y":0,"w":248,"h":248},
	"sourceSize": {"w":248,"h":248}
},
"P_1_WILD_D":
{
	"frame": {"x":1,"y":751,"w":248,"h":248},
	"rotated": false,
	"trimmed": false,
	"spriteSourceSize": {"x":0,"y":0,"w":248,"h":248},
	"sourceSize": {"w":248,"h":248}
},
"P_1_WILD_E":
{
	"frame": {"x":251,"y":1,"w":248,"h":248},
	"rotated": false,
	"trimmed": false,
	"spriteSourceSize": {"x":0,"y":0,"w":248,"h":248},
	"sourceSize": {"w":248,"h":248}
},
"P_1_WILD_F":
{
	"frame": {"x":501,"y":1,"w":248,"h":248},
	"rotated": false,
	"trimmed": false,
	"spriteSourceSize": {"x":0,"y":0,"w":248,"h":248},
	"sourceSize": {"w":248,"h":248}
},
"P_1_WILD_G":
{
	"frame": {"x":751,"y":1,"w":248,"h":248},
	"rotated": false,
	"trimmed": false,
	"spriteSourceSize": {"x":0,"y":0,"w":248,"h":248},
	"sourceSize": {"w":248,"h":248}
},
"P_1_WILD_H":
{
	"frame": {"x":251,"y":251,"w":248,"h":248},
	"rotated": false,
	"trimmed": false,
	"spriteSourceSize": {"x":0,"y":0,"w":248,"h":248},
	"sourceSize": {"w":248,"h":248}
},
"P_1_WILD_I":
{
	"frame": {"x":251,"y":501,"w":248,"h":248},
	"rotated": false,
	"trimmed": false,
	"spriteSourceSize": {"x":0,"y":0,"w":248,"h":248},
	"sourceSize": {"w":248,"h":248}
},
"P_1_WILD_J":
{
	"frame": {"x":251,"y":751,"w":248,"h":248},
	"rotated": false,
	"trimmed": false,
	"spriteSourceSize": {"x":0,"y":0,"w":248,"h":248},
	"sourceSize": {"w":248,"h":248}
},
"P_1_WILD_K":
{
	"frame": {"x":501,"y":251,"w":248,"h":248},
	"rotated": false,
	"trimmed": false,
	"spriteSourceSize": {"x":0,"y":0,"w":248,"h":248},
	"sourceSize": {"w":248,"h":248}
},
"P_1_WILD_L":
{
	"frame": {"x":751,"y":251,"w":248,"h":248},
	"rotated": false,
	"trimmed": false,
	"spriteSourceSize": {"x":0,"y":0,"w":248,"h":248},
	"sourceSize": {"w":248,"h":248}
},
"P_1_WILD_M":
{
	"frame": {"x":501,"y":501,"w":248,"h":248},
	"rotated": false,
	"trimmed": false,
	"spriteSourceSize": {"x":0,"y":0,"w":248,"h":248},
	"sourceSize": {"w":248,"h":248}
},
"P_1_WILD_N":
{
	"frame": {"x":501,"y":751,"w":248,"h":248},
	"rotated": false,
	"trimmed": false,
	"spriteSourceSize": {"x":0,"y":0,"w":248,"h":248},
	"sourceSize": {"w":248,"h":248}
}},
"meta": {
	"app": "https://www.codeandweb.com/texturepacker",
	"version": "1.0",
	"image": "P_1_WILD.png",
	"format": "RGBA8888",
	"size": {"w":1024,"h":1024},
	"scale": "1",
	"smartupdate": "$TexturePacker:SmartUpdate:f81374a725d671f85290411bd417a27b:000f9e891d13d8eb2e4292fa8c4add5d:41f5b6300b202d6d5868a0042299819d$"
}
}
